rpa_driver_downloader/__init__.py
rpa_driver_downloader/base.py
rpa_driver_downloader/chromium.py
rpa_driver_downloader/edge.py
rpa_driver_downloader/gecko.py
rpa_driver_downloader-0.2.0.dist-info/licenses/LICENSE
rpa_driver_downloader-0.2.0.dist-info/METADATA
rpa_driver_downloader-0.2.0.dist-info/WHEEL
rpa_driver_downloader-0.2.0.dist-info/top_level.txt
rpa_driver_downloader-0.2.0.dist-info/RECORD
